{
  "updated_at": "2026-03-22T04:58:00Z",
  "working_on": {
    "feature": "Project Handover and Knowledge Sync",
    "task": "Executing /save-brain for final persistent context",
    "status": "completed",
    "files": [
      ".brain/brain.json",
      "CHANGELOG.md",
      "docs/architecture/system_overview.md"
    ],
    "blockers": [],
    "notes": "System is transitioned to a professional standalone application."
  },
  "pending_tasks": [
    {
      "task": "Package as EXE",
      "priority": "medium",
      "notes": "User to run PyInstaller command as provided in walkthrough."
    }
  ],
  "recent_changes": [
    {
      "timestamp": "2026-03-22T04:50:00Z",
      "type": "feature",
      "description": "Implemented Universal Standalone GUI and Refactored Pipeline for logic-agnostic fiscal years.",
      "files": ["src/universal_app.py", "scripts/run_e2e.py", "src/parsers/"]
    }
  ],
  "decisions_made": [
    {
      "decision": "Transition to Functional Programming style for Pipeline",
      "reason": "Allows GUI to inject parameters (FY, Paths) easily without static global state."
    },
    {
      "decision": "Use ScrolledText for real-time GUI logging",
      "reason": "Provides professional feedback to non-tech users during long-running tasks."
    }
  ]
}
